{
  "id": "abs/hanging-straight-twisting-leg-hip-raise",
  "slug": "hanging-straight-twisting-leg-hip-raise",
  "name": "Hanging Straight Twisting Leg Hip Raise",
  "nameEs": "Elevación, hanging recto twisting pierna cadera",
  "muscle": "abs",
  "bodyPart": "core",
  "equipment": "other",
  "category": "strength",
  "secondaryMuscles": [],
  "instructions": [
    "Prepara el equipo y adopta la postura inicial.",
    "Activa el abs antes de iniciar el movimiento.",
    "Realiza el movimiento de forma controlada manteniendo la técnica.",
    "Vuelve a la posición inicial controlando la fase excéntrica.",
    "Mantén la respiración: exhala en el esfuerzo, inhala al volver."
  ],
  "file": "abs/hanging-straight-twisting-leg-hip-raise.gif",
  "gifUrl": "https://cdn.jsdelivr.net/gh/JahelCuadrado/ExerciseGymGifsDB@main/abs/hanging-straight-twisting-leg-hip-raise.gif"
}
