{
  "id": "lats/assisted-pull-up",
  "slug": "assisted-pull-up",
  "name": "Assisted Pull Up",
  "nameEs": "Dominada, assisted",
  "muscle": "lats",
  "bodyPart": "back",
  "equipment": "other",
  "category": "strength",
  "secondaryMuscles": [
    "biceps",
    "forearms",
    "delts"
  ],
  "instructions": [
    "Prepara el equipo y adopta la postura inicial.",
    "Activa el lats antes de iniciar el movimiento.",
    "Realiza el movimiento de forma controlada manteniendo la técnica.",
    "Vuelve a la posición inicial controlando la fase excéntrica.",
    "Mantén la respiración: exhala en el esfuerzo, inhala al volver."
  ],
  "file": "lats/assisted-pull-up.gif",
  "gifUrl": "https://cdn.jsdelivr.net/gh/JahelCuadrado/ExerciseGymGifsDB@main/lats/assisted-pull-up.gif"
}
